ssh_tunnel_manager/__init__.py
ssh_tunnel_manager/config.py
ssh_tunnel_manager/gui.py
ssh_tunnel_manager/icon.ico
ssh_tunnel_manager/main.py
ssh_tunnel_manager/startup_shortcut.py
ssh_tunnel_manager/utils.py
ssh_tunnel_manager_gui-0.2.4.dist-info/licenses/LICENSE
ssh_tunnel_manager_gui-0.2.4.dist-info/METADATA
ssh_tunnel_manager_gui-0.2.4.dist-info/WHEEL
ssh_tunnel_manager_gui-0.2.4.dist-info/entry_points.txt
ssh_tunnel_manager_gui-0.2.4.dist-info/top_level.txt
ssh_tunnel_manager_gui-0.2.4.dist-info/RECORD
