Metadata-Version: 2.4
Name: ssh-tunnel-manager-gui
Version: 0.2.4
Summary: A manager for SSH tunnels with a GUI.
Author-email: NtWriteCode <118625463+NtWriteCode@users.noreply.github.com>
License: MIT License
Project-URL: Homepage, https://github.com/NtWriteCode/ssh-tunnel-manager
Project-URL: Bug Tracker, https://github.com/NtWriteCode/ssh-tunnel-manager/issues
Keywords: ssh,tunnel,network,gui
Classifier: Development Status :: 4 - Beta
Classifier: Intended Audience :: Developers
Classifier: Intended Audience :: System Administrators
Classifier: License :: OSI Approved :: MIT License
Classifier: Programming Language :: Python :: 3
Classifier: Programming Language :: Python :: 3.8
Classifier: Programming Language :: Python :: 3.9
Classifier: Programming Language :: Python :: 3.10
Classifier: Programming Language :: Python :: 3.11
Classifier: Programming Language :: Python :: 3.12
Classifier: Topic :: System :: Networking
Classifier: Topic :: Utilities
Classifier: Framework :: Pytest
Classifier: Environment :: X11 Applications :: Qt
Classifier: Topic :: Software Development :: User Interfaces
Requires-Python: >=3.8
License-File: LICENSE
Requires-Dist: PyQt6>=6.0.0
Requires-Dist: typing-extensions>=4.0.0
Requires-Dist: PyYAML>=6.0.0
Provides-Extra: windows
Requires-Dist: pywin32>=300; extra == "windows"
Dynamic: license-file
